RandomWordGenerator/RandomWordGenerator.py
RandomWordGenerator/__init__.py
Random_Word_Generator-1.3.dist-info/METADATA
Random_Word_Generator-1.3.dist-info/WHEEL
Random_Word_Generator-1.3.dist-info/top_level.txt
Random_Word_Generator-1.3.dist-info/RECORD
