Metadata-Version: 2.1
Name: Random-Word-Generator
Version: 1.3
Summary: This is a random word generator module
Home-page: https://github.com/AbhishekSalian/Random-Word-Generator
Author: Abhishek C. Salian
Author-email: abhishek.c.salian@gmail.com
License: UNKNOWN
Platform: UNKNOWN
Classifier: Development Status :: 5 - Production/Stable
Classifier: Intended Audience :: Developers
Classifier: Operating System :: OS Independent
Classifier: Programming Language :: Python :: 3
Classifier: License :: OSI Approved :: MIT License
Classifier: Topic :: Software Development :: Libraries :: Python Modules
Classifier: Natural Language :: English
Requires-Python: >=3
